qai/server/__init__.py
qai/server/config.py
qai/server/mock/__init__.py
qai/server/mock/mock_functions.py
qai/server/mock/mock_responses.py
qai/server/mock/mockable.py
qai/server/models.py
qai/server/serve.py
qai/server/tools/__init__.py
qai/server/tools/security.py
qai_server-0.5.4.1.dist-info/METADATA
qai_server-0.5.4.1.dist-info/WHEEL
qai_server-0.5.4.1.dist-info/RECORD
